brightwind/__init__.py
brightwind/analyse/__init__.py
brightwind/analyse/analyse.py
brightwind/analyse/bw.mplstyle
brightwind/analyse/correlation.py
brightwind/analyse/plot.py
brightwind/analyse/shear.py
brightwind/demo_datasets/MERRA-2_NE_2000-01-01_2017-06-30.csv
brightwind/demo_datasets/MERRA-2_NW_2000-01-01_2017-06-30.csv
brightwind/demo_datasets/MERRA-2_SE_2000-01-01_2017-06-30.csv
brightwind/demo_datasets/MERRA-2_SW_2000-01-01_2017-06-30.csv
brightwind/demo_datasets/__init__.py
brightwind/demo_datasets/campbell_scientific_demo_data.csv
brightwind/demo_datasets/campbell_scientific_demo_data1.csv
brightwind/demo_datasets/demo_cleaning_file.csv
brightwind/demo_datasets/demo_cleaning_file2.csv
brightwind/demo_datasets/demo_cleaning_file3.csv
brightwind/demo_datasets/demo_cleaning_rules_file.json
brightwind/demo_datasets/demo_data.csv
brightwind/demo_datasets/demo_data2.csv
brightwind/demo_datasets/demo_data3.csv
brightwind/demo_datasets/demo_data4.csv
brightwind/demo_datasets/demo_data_adjusted_for_testing.csv
brightwind/demo_datasets/demo_data_iea43_wra_data_model.json
brightwind/demo_datasets/demo_floating_lidar_data.csv
brightwind/demo_datasets/floating_lidar_demo_iea43_wra_data_model_v1_2.json
brightwind/demo_datasets/floating_lidar_demo_iea43_wra_data_model_v1_3.json
brightwind/demo_datasets/iea43_wra_data_model.schema_v1_0.json
brightwind/demo_datasets/iea43_wra_data_model.schema_v1_2.json
brightwind/demo_datasets/iea43_wra_data_model_v1_0.json
brightwind/demo_datasets/sodar_iea43_wra_data_model_v1_3.json
brightwind/demo_datasets/solar_iea43_wra_data_model_v1_3.json
brightwind/demo_datasets/windographer_demo_data.txt
brightwind/demo_datasets/windographer_demo_data1.txt
brightwind/demo_datasets/windographer_demo_data2.txt
brightwind/demo_datasets/windographer_flagging_log.txt
brightwind/demo_datasets/windographer_flagging_log2.txt
brightwind/export/__init__.py
brightwind/export/export.py
brightwind/load/__init__.py
brightwind/load/cleaning_rule.schema.json
brightwind-2.3.0.dist-info/LICENSE.txt
brightwind-2.3.0.dist-info/METADATA
brightwind-2.3.0.dist-info/WHEEL
brightwind-2.3.0.dist-info/top_level.txt
brightwind-2.3.0.dist-info/RECORD
