Metadata-Version: 2.1
Name: brightwind
Version: 2.3.0
Summary: Scripts for wind resource data processing.
Home-page: https://github.com/brightwind-dev/brightwind.git
Download-URL: https://github.com/brightwind-dev/brightwind/archive/v2.3.0.tar.gz
Author: Stephen Holleran of BrightWind Ltd
Author-email: stephen@brightwindanalysis.com
License: MIT
Keywords: BRIGHT,WIND,RESOURCE,DATA,ANALYSTS,PROCESSING,WASP,ROSE,WINDFARMER,OPENWIND,WIND PRO,WINDOGRAPHER
Platform: UNKNOWN
Classifier: Programming Language :: Python :: 3.6
Classifier: Programming Language :: Python :: 3.7
Classifier: Programming Language :: Python :: 3.8
Classifier: Programming Language :: Python :: 3.9
Classifier: Programming Language :: Python :: 3.10
Classifier: Programming Language :: Python :: 3.11
Classifier: License :: OSI Approved :: MIT License
License-File: LICENSE.txt
Requires-Dist: pandas (<=2.0.1,>=0.24.0)
Requires-Dist: numpy (<2.0.0,>=1.16.4)
Requires-Dist: scikit-learn (>=0.19.1)
Requires-Dist: matplotlib (>=3.0.3)
Requires-Dist: requests (>=2.20.0)
Requires-Dist: scipy (>=0.19.1)
Requires-Dist: pytest (>=4.1.0)
Requires-Dist: six (>=1.12.0)
Requires-Dist: python-dateutil (>=2.8.0)
Requires-Dist: ipywidgets (>=7.4.2)
Requires-Dist: ipython (>=7.4.0)
Requires-Dist: gmaps (>=0.9.0)
Requires-Dist: colormap (>=1.0.1)
Requires-Dist: easydev (>=0.10.0)
Requires-Dist: jsonschema (>=4.17.3)
